README.rst
setup.cfg
setup.py
WCosa.egg-info/PKG-INFO
WCosa.egg-info/SOURCES.txt
WCosa.egg-info/dependency_links.txt
WCosa.egg-info/entry_points.txt
WCosa.egg-info/requires.txt
WCosa.egg-info/top_level.txt
wcosa/__init__.py
wcosa/boards.json
wcosa/info.py
wcosa/settings.json
wcosa/wcosa.py
wcosa/../templates/cmake/CMakeLists.txt.tpl
wcosa/../templates/config/config.json.tpl
wcosa/../templates/config/internal-config.json.tpl
wcosa/../templates/examples/main.cpp
wcosa/../templates/gitignore-files/.gitignore-clion
wcosa/../templates/gitignore-files/.gitignore-general
wcosa/../templates/ide/clion/CMakeLists.txt.tpl
wcosa/../templates/ide/clion/CMakeListsPrivate.txt.tpl
wcosa/../toolchain/CMakeLists.txt
wcosa/../toolchain/README.md
wcosa/../toolchain/arduino-cmake/.editorconfig
wcosa/../toolchain/arduino-cmake/.git
wcosa/../toolchain/arduino-cmake/.gitattributes
wcosa/../toolchain/arduino-cmake/.gitignore
wcosa/../toolchain/arduino-cmake/.travis.yml
wcosa/../toolchain/arduino-cmake/CHANGELOG.md
wcosa/../toolchain/arduino-cmake/CMakeLists.txt
wcosa/../toolchain/arduino-cmake/CONTRIBUTING.md
wcosa/../toolchain/arduino-cmake/README.rst
wcosa/../toolchain/arduino-cmake/.idea/codeStyleSettings.xml
wcosa/../toolchain/arduino-cmake/.idea/codeStyles/Project.xml
wcosa/../toolchain/arduino-cmake/.idea/codeStyles/codeStyleConfig.xml
wcosa/../toolchain/arduino-cmake/cmake/ArduinoToolchain.cmake
wcosa/../toolchain/arduino-cmake/cmake/Platform/Arduino.cmake
wcosa/../toolchain/arduino-cmake/cmake/Platform/Core/BoardPropertiesReader.cmake
wcosa/../toolchain/arduino-cmake/cmake/Platform/Core/LibraryFinder.cmake
wcosa/../toolchain/arduino-cmake/cmake/Platform/Core/SourceFinder.cmake
wcosa/../toolchain/arduino-cmake/cmake/Platform/Core/VariableValidator.cmake
wcosa/../toolchain/arduino-cmake/cmake/Platform/Core/BoardFlags/CompilerFlagsSetter.cmake
wcosa/../toolchain/arduino-cmake/cmake/Platform/Core/BoardFlags/FlagsSetter.cmake
wcosa/../toolchain/arduino-cmake/cmake/Platform/Core/BoardFlags/LinkerFlagsSetter.cmake
wcosa/../toolchain/arduino-cmake/cmake/Platform/Core/Examples/ArduinoExampleFactory.cmake
