Metadata-Version: 1.1
Name: WCosa
Version: 1.1.1
Summary: Create, Build, Upload and Monitor AVR Cosa Projects
Home-page: UNKNOWN
Author: Deep Dhillon, Jeff Niu
Author-email: deep@deepdhillon.com, jeffniu22@gmail.com, ambareeshbalaji@gmail.com
License: MIT
Keywords: iot,embedded,arduino,avr,fpga,firmware,hardware,microcontroller,debug,cosa,tool
Platform: UNKNOWN
Classifier: Development Status :: 4 - Beta
